pywam/__init__.py
pywam/attributes.py
pywam/client.py
pywam/events.py
pywam/speaker.py
pywam/lib/__init__.py
pywam/lib/api_call.py
pywam/lib/api_response.py
pywam/lib/const.py
pywam/lib/equalizer.py
pywam/lib/exceptions.py
pywam/lib/helpers.py
pywam/lib/http.py
pywam/lib/media_presets.py
pywam/lib/translate.py
pywam/lib/validate.py
pywam-0.0.1.dist-info/LICENSE.txt
pywam-0.0.1.dist-info/METADATA
pywam-0.0.1.dist-info/WHEEL
pywam-0.0.1.dist-info/top_level.txt
pywam-0.0.1.dist-info/RECORD
