Metadata-Version: 2.1
Name: pywam
Version: 0.0.1
Summary: Library built on AsyncIO for communicating with Samsung Wireless Audio speakers (WAM).
Author: Daniel Jönsson
License: MIT License
Project-URL: Homepage, https://www.github.com/Strixx76/pywam
Classifier: Development Status :: 3 - Alpha
Classifier: Framework :: AsyncIO
Classifier: Programming Language :: Python :: 3
Classifier: License :: OSI Approved :: MIT License
Classifier: Typing :: Typed
Classifier: Operating System :: OS Independent
Classifier: Intended Audience :: Developers
Requires-Python: >=3.8
License-File: LICENSE.txt
